ppr_handler/__init__.py
ppr_handler/py.typed
ppr_handler-0.0.2.dist-info/LICENSE
ppr_handler-0.0.2.dist-info/METADATA
ppr_handler-0.0.2.dist-info/WHEEL
ppr_handler-0.0.2.dist-info/top_level.txt
ppr_handler-0.0.2.dist-info/RECORD
