Metadata-Version: 2.1
Name: ppr-handler
Version: 0.0.2
Summary: urllib.request handler for scheme ppr: Python Package Resource files.
Author-email: Filip Thyssen <filip.thyssen@gmail.com>
License: MIT License
Project-URL: Homepage, https://github.com/fthyssen/ppr-handler
Project-URL: Repository, https://github.com/fthyssen/ppr-handler
Keywords: ppr,urllib
Classifier: Programming Language :: Python :: 3
Classifier: Operating System :: OS Independent
Requires-Python: >=3.7
License-File: LICENSE
Requires-Dist: importlib-resources >=1.3 ; python_version < "3.9"
